paxexpress_cli/__init__.py
paxexpress_cli/authentication/__init__.py
paxexpress_cli/authentication/cli.py
paxexpress_cli/authentication/core.py
paxexpress_cli/authentication/models.py
paxexpress_cli/cli.py
paxexpress_cli/files/__init__.py
paxexpress_cli/files/cli.py
paxexpress_cli/files/core.py
paxexpress_cli/files/models.py
paxexpress_cli/icon.png
paxexpress_cli/packages/__init__.py
paxexpress_cli/packages/cli.py
paxexpress_cli/packages/core.py
paxexpress_cli/packages/models.py
paxexpress_cli/repositories/__init__.py
paxexpress_cli/repositories/cli.py
paxexpress_cli/repositories/core.py
paxexpress_cli/repositories/models.py
paxexpress_cli/settings.py
paxexpress_cli/utils.py
paxexpress_cli/versions/__init__.py
paxexpress_cli/versions/cli.py
paxexpress_cli/versions/core.py
paxexpress_cli/versions/models.py
paxexpress_cli-0.2.0.dist-info/entry_points.txt
paxexpress_cli-0.2.0.dist-info/WHEEL
paxexpress_cli-0.2.0.dist-info/METADATA
paxexpress_cli-0.2.0.dist-info/RECORD
